<EnergyLabel xmlns="http://www.ens.dk/EnergyLabel"><SchemaVersion>2.0.1</SchemaVersion><EnergyLabelType><BasedOn>CalculatedConsumption</BasedOn><Usage>SingleFamily</Usage><IsNewBuild>false</IsNewBuild><IsMixedUsage>false</IsMixedUsage></EnergyLabelType><EnergyLabelSoftware><Name>Energy10</Name><Version>1.00</Version></EnergyLabelSoftware><CalculationSoftware><Name>Be18</Name><Version>10.19.7.22</Version></CalculationSoftware><Submitter><Company><Number>600078</Number><Name>Botjek A/S</Name><Address><StreetName xmlns="http://www.ens.dk/Globals">Botjek Center Fyn, Thriges Plads 10</StreetName><HouseNumber xmlns="http://www.ens.dk/Globals" /><PostalCode xmlns="http://www.ens.dk/Globals">5000</PostalCode><PostalCity xmlns="http://www.ens.dk/Globals">Odense C</PostalCity></Address><PhoneNumber>70261199</PhoneNumber><Email>fyn@botjek.dk</Email></Company><Consultant><ID>404195</ID><Name>Michael Bo Bang </Name><Email>mbb@botjek.dk</Email></Consultant></Submitter><ReplaceEnergyLabelSerialIdentifier>0</ReplaceEnergyLabelSerialIdentifier><EnergyLabelSerialIdentifier>311896657</EnergyLabelSerialIdentifier><ValidFrom>2026-04-24</ValidFrom><ValidTo>2036-04-24</ValidTo><InputData xmlns="http://www.ens.dk/InputData"><Label><Address><Name xmlns="http://www.ens.dk/Globals" /><StreetName xmlns="http://www.ens.dk/Globals">Sønderskovvej</StreetName><HouseNumber xmlns="http://www.ens.dk/Globals">5</HouseNumber><Floor xmlns="http://www.ens.dk/Globals" /><SideOrDoor xmlns="http://www.ens.dk/Globals" /><PostalCode xmlns="http://www.ens.dk/Globals">5932</PostalCode><PostalCity xmlns="http://www.ens.dk/Globals">Humble</PostalCity><StreetCode xmlns="http://www.ens.dk/Globals">784</StreetCode></Address><BBR><MunicipalityNumber>482</MunicipalityNumber><PropertyNumber>5790</PropertyNumber><BFENumber>3072422</BFENumber></BBR><ReviewDate>2026-03-24</ReviewDate><Ownership>Private</Ownership><ProposalGroups><ProposalGroup ID="0"><ShortText>Efterisolering af loftsrum med 150 mm isolering til 350 mm</ShortText><LongText>Efterisolering af loftsrum med 150 mm isolering. Eksisterende isolering bevares, så der efter fremtidige forhold er isoleret med 350 mm. Der etableres ny gangbro i tagrummet, eller hvis der findes en eksisterende, skal denne hæves til de nye isoleringsforhold.</LongText><IsRecommended>false</IsRecommended><Investment>32425</Investment><IsInvestmentOverridden>false</IsInvestmentOverridden><BIClassification>1-1-1-0</BIClassification><ProposalReferences><ProposalReference ProposalID="0" /></ProposalReferences></ProposalGroup><ProposalGroup ID="1"><ShortText>Udskiftning af eksisterende yderdøre</ShortText><LongText>Eksisterende yderdøre foreslås udskiftet til nye døre med bedre isolering og tæthed.</LongText><IsRecommended>false</IsRecommended><Investment>26082</Investment><IsInvestmentOverridden>false</IsInvestmentOverridden><BIClassification>1-3-3-0</BIClassification><ProposalReferences><ProposalReference ProposalID="1" /><ProposalReference ProposalID="2" /></ProposalReferences></ProposalGroup><ProposalGroup ID="2"><ShortText>Udskiftning af eksisterende flerfagsvinduer</ShortText><LongText>Eksisterende flerfagsvinduer foreslås udskiftet til nye vinduer med energiruder, energiklasse A.</LongText><IsRecommended>false</IsRecommended><Investment>78936</Investment><IsInvestmentOverridden>false</IsInvestmentOverridden><BIClassification>1-3-1-0</BIClassification><ProposalReferences><ProposalReference ProposalID="3" /><ProposalReference ProposalID="4" /><ProposalReference ProposalID="5" /><ProposalReference ProposalID="6" /><ProposalReference ProposalID="7" /><ProposalReference ProposalID="8" /></ProposalReferences></ProposalGroup><ProposalGroup ID="3"><ShortText>Montage af nye solceller</ShortText><LongText>Montering af solceller på tagflade mod syd . Det anbefales at der monteres solceller af typen Monokrystallinske silicium med et areal på ca. 20 m². Det forslåede anlæg har en effekt på 4,2 kW. For at opnå optimal virkningsgrad kan det være nødvendigt at beskære eventuelle trækroner, så der ikke opstår skyggevirkning på solcellerne. Det bør undersøges, om den eksisterende tagkonstruktion er egnet til den ekstra vægt fra solcellerne. En eventuel udgift til dette er ikke medtaget i forslagets økonomi. I det foreslåede anlæg er der ikke  taget højde for eventuelle restriktioner i forhold til Planlovsbestemmelser herunder lokalplan m.v. 
Modsat solvarme og varmepumpe, supplerer solceller strømforsyningen og ikke varmeforsyningen, hvis der ikke anvendes el til opvarmning af bygningen.</LongText><IsRecommended>true</IsRecommended><Investment>40800</Investment><ImplementationReferenceText>Solcelleanlæg</ImplementationReferenceText><ImplementationReferenceLink>www.sparenergi.dk/solcelleanlaeg</ImplementationReferenceLink><RenovationTime>Fra 1 uge til 2 uger</RenovationTime><IsInvestmentOverridden>false</IsInvestmentOverridden><BIClassification>4-1-3-0</BIClassification><ProposalReferences><ProposalReference ProposalID="9" /></ProposalReferences></ProposalGroup></ProposalGroups><Comments><Additional>Bygningsdelenes isoleringsevne er baseret på skøn ud fra registrerede isoleringstykkelser, og er heraf fastlagt ud fra tabeller i gældende håndbog for energikonsulenter, som sammen med gældende DS 418 og f.eks Rockwool Energy Design danner grundlag for beregninger af yderligere konstruktioner.

Der gøres opmærksom på, at forslag vedr. efterisolering af bygningskonstruktioner som f.eks. gulve, lofter og vægge alene er beregnet ud fra et energimæssigt hensyn. Der er i forslagene ikke taget højde for byggetekniske konsekvenser af forslagene. 

Det anbefales generelt at kontakte en rådgiver/fagmand, for at få udarbejdet en detaljeret projektbeskrivelse før isolerings- og/eller ombygningsarbejder igangsættes. I forbindelse med rapportens forslag om energiforbedring af tekniske installationer, bør man altid søge teknisk sparring med en professionel rådgiver eller leverandør. I forhold til energimærkets gyldighedsperiode, vil både prisgrundlag og produktudviklingen kunne ændre sig en del, år for år.

Ved bygningsgennemgangen forelå udfyldt ejeroplysningsskema.

Renoveringstider, som fremgår ved "Rentable forslag", er estimerede tider.

Det er vigtigt at være opmærksom på, at energimæssige forbedringer ikke kun har betydning for bygningens energiforbrug, men også for den daglige komfort, samt for en eventuel gensalgsværdi for ejendommen.  
                                                                                                                                                                                                                                                               
Svingende energipriser har ikke betydning for bygningers energimærke, men har indflydelse på energiøkonomien. 

Ved høje energipriser kan værdien af besparelsesforslag blive større, hvilket betyder, at det kan give økonomisk mening at gennemføre flere forslag inklusiv forslag der kan være rentable, hvis de udføres sammen med andre renoveringer.

Ved lave energipriser kan værdien af besparelsesforslag blive mindre og/eller umiddelbart ikke økonomisk rentable. I forbindelse hermed, er det vigtigt at være opmærksom på, at energimæssige forbedringer ikke kun har betydning for bygningens energiforbrug, men også for den daglige komfort, samt for en eventuel gensalgsværdi for ejendommen.</Additional><OnEnergyPrices>Der er i energimærket anvendt aktuelle energipriser for el.

Rapportens elpris er anvendt ud fra en gennemsnitsvurdering, da energipriserne varierer dagligt og i forhold til valg af leverandør.
 
Til beregning af rapportens forbedringsforslag er der anvendt estimerede priser, der kan variere en del fra aktuelle tilbudspriser, afhængig af både regionale forhold og valg af leverandør. 
I forbindelse med rapportens forslag om energiforbedringer, bør man altid søge  sparring med en professionel rådgiver eller leverandør. 
I forhold til energimærkets gyldighedsperiode, vil både prisgrundlag og produktudviklingen kunne ændre sig en del, år for år.</OnEnergyPrices><OnBuildingDescription>De opmålte opvarmede arealer og BBR-arealer, samt opførelsestidspunkt og evt. renoveringstidspunkt, kan ses under baggrundsinformation.

Ejendommen er kontrolopmålt af energikonsulenten ud fra stikprøver og bygningstegninger. 

De opmålte opvarmede arealer stemmer overens med BBR-meddelelsen. 

Arealerne forudsættes jf. gældende Håndbog for energikonsulenter opvarmet med samme opvarmningsform som resten af bygningen, uanset at der ingen varmekilde er, da det vurderes at eksisterende varmeanlæg er tilstrækkelig til at kunne opvarme hele boligen 

Hvis ikke andet er angivet, så er de faktuelle oplysninger i energimærket baseret på skøn ud fra hvad der visuelt kan konstateres. Oplysningerne er ikke en garanti og kan ikke betragtes som dette, men er angivet for at informere om hvad der er anvendt som grundlag for beregningen.</OnBuildingDescription></Comments><Buildings><Building ID="0"><Address><Name xmlns="http://www.ens.dk/Globals">Hovedbygning</Name><StreetName xmlns="http://www.ens.dk/Globals">Sønderskovvej</StreetName><HouseNumber xmlns="http://www.ens.dk/Globals">5</HouseNumber><Floor xmlns="http://www.ens.dk/Globals" /><SideOrDoor xmlns="http://www.ens.dk/Globals" /><PostalCode xmlns="http://www.ens.dk/Globals">5932</PostalCode><PostalCity xmlns="http://www.ens.dk/Globals">Humble</PostalCity><StreetCode xmlns="http://www.ens.dk/Globals">784</StreetCode></Address><BBR><BuildingNumber>1</BuildingNumber><UseCode>120</UseCode><YearOfConstruction>1850</YearOfConstruction><YearOfRenovation>1963</YearOfRenovation><DwellingArea>100</DwellingArea><CommercialArea>0</CommercialArea></BBR><ReportedConsumptions /><LoggedConsumptions></LoggedConsumptions><Zones><Zone ID="0"><Name>Hovedbygning</Name><Usage>SingleFamily</Usage><SubtractWindowAreaFromOuterWalls>true</SubtractWindowAreaFromOuterWalls><BBRUseCode>120</BBRUseCode><BuildingType>DetachedBuilding</BuildingType><HousingUnits>1</HousingUnits><FloorCount>1</FloorCount><Height>2.3</Height><UsageDays>7</UsageDays><UsageFrom>0</UsageFrom><UsageTo>24</UsageTo><TotalHeatedFloorArea>100</TotalHeatedFloorArea><TopFloorAreaOfHeatedFloorArea>0</TopFloorAreaOfHeatedFloorArea><BasementAreaOfHeatedFloorArea>0</BasementAreaOfHeatedFloorArea><UnheatedBasementArea>0</UnheatedBasementArea><HeatCapacity>105</HeatCapacity><Rotation>0</Rotation><AdditionToEnergyFrame>0</AdditionToEnergyFrame><SetPointHeatedTemperature>20</SetPointHeatedTemperature><SetPointWantedTemperature>23</SetPointWantedTemperature><SetPointNaturalVentilationTemperature>24</SetPointNaturalVentilationTemperature><SetPointCoolingTemperature>25</SetPointCoolingTemperature><SetPointStoreTemperature>20</SetPointStoreTemperature><DimensioningRoomTemperature>20</DimensioningRoomTemperature><DimensioningOuterTemperature>-12</DimensioningOuterTemperature><DimensioningStoreTemperature>20</DimensioningStoreTemperature><ElectricityPriceForHeating>1.63</ElectricityPriceForHeating><ElectricityPriceForNonHeating>1.63</ElectricityPriceForNonHeating><ElectricityPriceForExcessProduction>0.15</ElectricityPriceForExcessProduction><YearlyFeeForExcessProductionOfElectricity>0</YearlyFeeForExcessProductionOfElectricity><EstimatedElectricityConsumptionForNonHeating>35</EstimatedElectricityConsumptionForNonHeating><SunBurdenedRooms /><Statuses><Status ID="0"><ShortText>Massiv ydervæg - 24 cm tegl - 150 mm indvendig isolering</ShortText><LongText>Ydervægge består af 24 cm massiv teglvæg med indvendig pladebeklædning og 150 mm isolering. Konstruktions- og isoleringsforhold er baseret på ejers oplysninger.
Konstruktionstykkelse er målt ved vindue. Konstruktionstykkelse, sammenholdt med opførelsesår, ligger til grund for skønnet af isoleringsforholdet.</LongText><BIClassification>1-2-2-0</BIClassification><BuildingUnit><BuildingPart xmlns="http://www.ens.dk/BuildingUnits"><Area>97.6</Area><UValue>0.22</UValue><BFactor>1</BFactor><DimensioningOuterTemperature>-12</DimensioningOuterTemperature><DimensioningInnerTemperature>20</DimensioningInnerTemperature></BuildingPart></BuildingUnit><Proposals /></Status><Status ID="1"><ShortText>Linjetab: Massiv ydervæg - 24 cm tegl - 150 mm indvendig isolering</ShortText><LongText /><BIClassification>1-3-4-0</BIClassification><BuildingUnit><LinearThermalTransmittance xmlns="http://www.ens.dk/BuildingUnits"><Length>42</Length><HeatLoss>0.04</HeatLoss><BFactor>1</BFactor><DimensioningOuterTemperature>-12</DimensioningOuterTemperature><DimensioningInnerTemperature>20</DimensioningInnerTemperature></LinearThermalTransmittance></BuildingUnit><Proposals /></Status><Status ID="2"><ShortText>Terrændæk - Beton med slidlag - 300 mm polystyrenplader - skillevægsfundament (beton)</ShortText><LongText>Terrændæk er udført af beton med slidlagsgulv. Gulvet er isoleret med 300 mm polystyrenplader under betonen. Konstruktions- og isoleringsforhold er baseret på ejers oplysninger.
( U-værdi tillæg påført: 0.07 W/m2K)</LongText><BIClassification>1-4-1-0</BIClassification><BuildingUnit><BuildingPart xmlns="http://www.ens.dk/BuildingUnits"><Area>87.19</Area><UValue>0.16</UValue><BFactor>1</BFactor><DimensioningOuterTemperature>-12</DimensioningOuterTemperature><DimensioningInnerTemperature>20</DimensioningInnerTemperature></BuildingPart></BuildingUnit><Proposals /></Status><Status ID="3"><ShortText>Loftsrum - 200 mm isolering med spær ≥ 200 mm</ShortText><LongText>Loftsrum vurderes isoleret med 200 mm mineraluld. Konstruktionstykkelse er målt ved loftlem. Konstruktionstykkelse, sammenholdt med opførelsesår, ligger til grund for skønnet af isoleringsforholdet.</LongText><BIClassification>1-1-1-0</BIClassification><BuildingUnit><BuildingPart xmlns="http://www.ens.dk/BuildingUnits"><Area>103.1</Area><UValue>0.23</UValue><BFactor>1</BFactor><DimensioningOuterTemperature>-12</DimensioningOuterTemperature><DimensioningInnerTemperature>20</DimensioningInnerTemperature></BuildingPart></BuildingUnit><Proposals><Proposal ID="0"><ShortText>Efterisolering af loftsrum med 150 mm isolering til 350 mm</ShortText><LongText>Efterisolering af loftsrum med 150 mm isolering. Eksisterende isolering bevares, så der efter fremtidige forhold er isoleret med 350 mm. Der etableres ny gangbro i tagrummet, eller hvis der findes en eksisterende, skal denne hæves til de nye isoleringsforhold.</LongText><LifeTime>40</LifeTime><Investment>32425</Investment><ProposeToTearDown>false</ProposeToTearDown><BIClassification>1-1-1-0</BIClassification><BuildingUnit><BuildingPart xmlns="http://www.ens.dk/BuildingUnits"><Area>103.1</Area><UValue>0.13</UValue><BFactor>1</BFactor><DimensioningOuterTemperature>-12</DimensioningOuterTemperature><DimensioningInnerTemperature>20</DimensioningInnerTemperature></BuildingPart></BuildingUnit></Proposal></Proposals></Status><Status ID="4"><ShortText>Yderdør med 1 rude - 2 lags termorude</ShortText><LongText>Yderdør med enkeltfagsvindue, monteret med tolags termoruder.</LongText><BIClassification>1-3-3-0</BIClassification><BuildingUnit><Window xmlns="http://www.ens.dk/BuildingUnits"><NumberOfWindows>1</NumberOfWindows><Orientation>283</Orientation><Inclination>90</Inclination><Area>1.7</Area><UValue>2.7</UValue><BFactor>1</BFactor><GlassShare>0.57</GlassShare><SolarHeatTransmittance>0.75</SolarHeatTransmittance><SolarScreening>1</SolarScreening><OuterWallID>0</OuterWallID><Shade><ShortText>Standard anvendelseskode 110, 120 og 130 iht. HB2017</ShortText><Horizon>20</Horizon><Eaves>20</Eaves><Left>20</Left><Right>20</Right><WindowHole>10</WindowHole></Shade><DimensioningOuterTemperature>-12</DimensioningOuterTemperature><DimensioningInnerTemperature>20</DimensioningInnerTemperature><IsInMostSunBurdenedRoom>false</IsInMostSunBurdenedRoom></Window></BuildingUnit><Proposals><Proposal ID="1"><ShortText>Udskiftning af eksisterende yderdøre</ShortText><LongText>Eksisterende yderdøre foreslås udskiftet til nye døre med bedre isolering og tæthed.</LongText><LifeTime>30</LifeTime><Investment>13770</Investment><ProposeToTearDown>false</ProposeToTearDown><BIClassification>1-3-3-0</BIClassification><BuildingUnit><Window xmlns="http://www.ens.dk/BuildingUnits"><NumberOfWindows>1</NumberOfWindows><Orientation>283</Orientation><Inclination>90</Inclination><Area>1.7</Area><UValue>0.8</UValue><BFactor>1</BFactor><GlassShare>0.64</GlassShare><SolarHeatTransmittance>0.51</SolarHeatTransmittance><SolarScreening>1</SolarScreening><OuterWallID>0</OuterWallID><Shade><ShortText>Standard anvendelseskode 110, 120 og 130 iht. HB2017</ShortText><Horizon>20</Horizon><Eaves>20</Eaves><Left>20</Left><Right>20</Right><WindowHole>10</WindowHole></Shade><DimensioningOuterTemperature>-12</DimensioningOuterTemperature><DimensioningInnerTemperature>20</DimensioningInnerTemperature><IsInMostSunBurdenedRoom>false</IsInMostSunBurdenedRoom></Window></BuildingUnit></Proposal></Proposals></Status><Status ID="5"><ShortText>Yderdør med 1 rude - 2 lags termorude</ShortText><LongText>Yderdør med enkeltfagsvindue, monteret med tolags termoruder.</LongText><BIClassification>1-3-3-0</BIClassification><BuildingUnit><Window xmlns="http://www.ens.dk/BuildingUnits"><NumberOfWindows>1</NumberOfWindows><Orientation>13</Orientation><Inclination>90</Inclination><Area>1.52</Area><UValue>2.7</UValue><BFactor>1</BFactor><GlassShare>0.57</GlassShare><SolarHeatTransmittance>0.75</SolarHeatTransmittance><SolarScreening>1</SolarScreening><OuterWallID>0</OuterWallID><Shade><ShortText>Standard anvendelseskode 110, 120 og 130 iht. HB2017</ShortText><Horizon>20</Horizon><Eaves>20</Eaves><Left>20</Left><Right>20</Right><WindowHole>10</WindowHole></Shade><DimensioningOuterTemperature>-12</DimensioningOuterTemperature><DimensioningInnerTemperature>20</DimensioningInnerTemperature><IsInMostSunBurdenedRoom>false</IsInMostSunBurdenedRoom></Window></BuildingUnit><Proposals><Proposal ID="2"><ShortText>Udskiftning af eksisterende yderdøre</ShortText><LongText>Eksisterende yderdøre foreslås udskiftet til nye døre med bedre isolering og tæthed.</LongText><LifeTime>30</LifeTime><Investment>12312</Investment><ProposeToTearDown>false</ProposeToTearDown><BIClassification>1-3-3-0</BIClassification><BuildingUnit><Window xmlns="http://www.ens.dk/BuildingUnits"><NumberOfWindows>1</NumberOfWindows><Orientation>13</Orientation><Inclination>90</Inclination><Area>1.52</Area><UValue>0.8</UValue><BFactor>1</BFactor><GlassShare>0.64</GlassShare><SolarHeatTransmittance>0.51</SolarHeatTransmittance><SolarScreening>1</SolarScreening><OuterWallID>0</OuterWallID><Shade><ShortText>Standard anvendelseskode 110, 120 og 130 iht. HB2017</ShortText><Horizon>20</Horizon><Eaves>20</Eaves><Left>20</Left><Right>20</Right><WindowHole>10</WindowHole></Shade><DimensioningOuterTemperature>-12</DimensioningOuterTemperature><DimensioningInnerTemperature>20</DimensioningInnerTemperature><IsInMostSunBurdenedRoom>false</IsInMostSunBurdenedRoom></Window></BuildingUnit></Proposal></Proposals></Status><Status ID="6"><ShortText>Flerfagsvindue med gående rammer - 2 lags termorude kold kant</ShortText><LongText>Oplukkelige vinduer med flere fag. Vinduerne er monteret med tolags termorude.</LongText><BIClassification>1-3-1-0</BIClassification><BuildingUnit><Window xmlns="http://www.ens.dk/BuildingUnits"><NumberOfWindows>1</NumberOfWindows><Orientation>103</Orientation><Inclination>90</Inclination><Area>0.95</Area><UValue>2.7</UValue><BFactor>1</BFactor><GlassShare>0.57</GlassShare><SolarHeatTransmittance>0.75</SolarHeatTransmittance><SolarScreening>1</SolarScreening><OuterWallID>0</OuterWallID><Shade><ShortText>Standard anvendelseskode 110, 120 og 130 iht. HB2017</ShortText><Horizon>20</Horizon><Eaves>20</Eaves><Left>20</Left><Right>20</Right><WindowHole>10</WindowHole></Shade><DimensioningOuterTemperature>-12</DimensioningOuterTemperature><DimensioningInnerTemperature>20</DimensioningInnerTemperature><IsInMostSunBurdenedRoom>false</IsInMostSunBurdenedRoom></Window></BuildingUnit><Proposals><Proposal ID="3"><ShortText>Udskiftning af eksisterende flerfagsvinduer</ShortText><LongText>Eksisterende flerfagsvinduer foreslås udskiftet til nye vinduer med energiruder, energiklasse A.</LongText><LifeTime>30</LifeTime><Investment>6270</Investment><ProposeToTearDown>false</ProposeToTearDown><BIClassification>1-3-1-0</BIClassification><BuildingUnit><Window xmlns="http://www.ens.dk/BuildingUnits"><NumberOfWindows>1</NumberOfWindows><Orientation>103</Orientation><Inclination>90</Inclination><Area>0.95</Area><UValue>0.8</UValue><BFactor>1</BFactor><GlassShare>0.74</GlassShare><SolarHeatTransmittance>0.51</SolarHeatTransmittance><SolarScreening>1</SolarScreening><OuterWallID>0</OuterWallID><Shade><ShortText>Standard anvendelseskode 110, 120 og 130 iht. HB2017</ShortText><Horizon>20</Horizon><Eaves>20</Eaves><Left>20</Left><Right>20</Right><WindowHole>10</WindowHole></Shade><DimensioningOuterTemperature>-12</DimensioningOuterTemperature><DimensioningInnerTemperature>20</DimensioningInnerTemperature><IsInMostSunBurdenedRoom>false</IsInMostSunBurdenedRoom></Window></BuildingUnit></Proposal></Proposals></Status><Status ID="7"><ShortText>Flerfagsvindue med gående rammer - 2 lags termorude kold kant</ShortText><LongText>Oplukkelige vinduer med flere fag. Vinduerne er monteret med tolags termorude.</LongText><BIClassification>1-3-1-0</BIClassification><BuildingUnit><Window xmlns="http://www.ens.dk/BuildingUnits"><NumberOfWindows>3</NumberOfWindows><Orientation>283</Orientation><Inclination>90</Inclination><Area>1.27</Area><UValue>2.7</UValue><BFactor>1</BFactor><GlassShare>0.57</GlassShare><SolarHeatTransmittance>0.75</SolarHeatTransmittance><SolarScreening>1</SolarScreening><OuterWallID>0</OuterWallID><Shade><ShortText>Standard anvendelseskode 110, 120 og 130 iht. HB2017</ShortText><Horizon>20</Horizon><Eaves>20</Eaves><Left>20</Left><Right>20</Right><WindowHole>10</WindowHole></Shade><DimensioningOuterTemperature>-12</DimensioningOuterTemperature><DimensioningInnerTemperature>20</DimensioningInnerTemperature><IsInMostSunBurdenedRoom>false</IsInMostSunBurdenedRoom></Window></BuildingUnit><Proposals><Proposal ID="4"><ShortText>Udskiftning af eksisterende flerfagsvinduer</ShortText><LongText>Eksisterende flerfagsvinduer foreslås udskiftet til nye vinduer med energiruder, energiklasse A.</LongText><LifeTime>30</LifeTime><Investment>25212</Investment><ProposeToTearDown>false</ProposeToTearDown><BIClassification>1-3-1-0</BIClassification><BuildingUnit><Window xmlns="http://www.ens.dk/BuildingUnits"><NumberOfWindows>3</NumberOfWindows><Orientation>283</Orientation><Inclination>90</Inclination><Area>1.27</Area><UValue>0.8</UValue><BFactor>1</BFactor><GlassShare>0.74</GlassShare><SolarHeatTransmittance>0.51</SolarHeatTransmittance><SolarScreening>1</SolarScreening><OuterWallID>0</OuterWallID><Shade><ShortText>Standard anvendelseskode 110, 120 og 130 iht. HB2017</ShortText><Horizon>20</Horizon><Eaves>20</Eaves><Left>20</Left><Right>20</Right><WindowHole>10</WindowHole></Shade><DimensioningOuterTemperature>-12</DimensioningOuterTemperature><DimensioningInnerTemperature>20</DimensioningInnerTemperature><IsInMostSunBurdenedRoom>false</IsInMostSunBurdenedRoom></Window></BuildingUnit></Proposal></Proposals></Status><Status ID="8"><ShortText>Flerfagsvindue med gående rammer - 2 lags termorude kold kant</ShortText><LongText>Oplukkelige vinduer med flere fag. Vinduerne er monteret med tolags termorude.</LongText><BIClassification>1-3-1-0</BIClassification><BuildingUnit><Window xmlns="http://www.ens.dk/BuildingUnits"><NumberOfWindows>1</NumberOfWindows><Orientation>283</Orientation><Inclination>90</Inclination><Area>1.12</Area><UValue>2.7</UValue><BFactor>1</BFactor><GlassShare>0.57</GlassShare><SolarHeatTransmittance>0.75</SolarHeatTransmittance><SolarScreening>1</SolarScreening><OuterWallID>0</OuterWallID><Shade><ShortText>Standard anvendelseskode 110, 120 og 130 iht. HB2017</ShortText><Horizon>20</Horizon><Eaves>20</Eaves><Left>20</Left><Right>20</Right><WindowHole>10</WindowHole></Shade><DimensioningOuterTemperature>-12</DimensioningOuterTemperature><DimensioningInnerTemperature>20</DimensioningInnerTemperature><IsInMostSunBurdenedRoom>false</IsInMostSunBurdenedRoom></Window></BuildingUnit><Proposals><Proposal ID="5"><ShortText>Udskiftning af eksisterende flerfagsvinduer</ShortText><LongText>Eksisterende flerfagsvinduer foreslås udskiftet til nye vinduer med energiruder, energiklasse A.</LongText><LifeTime>30</LifeTime><Investment>7392</Investment><ProposeToTearDown>false</ProposeToTearDown><BIClassification>1-3-1-0</BIClassification><BuildingUnit><Window xmlns="http://www.ens.dk/BuildingUnits"><NumberOfWindows>1</NumberOfWindows><Orientation>283</Orientation><Inclination>90</Inclination><Area>1.12</Area><UValue>0.8</UValue><BFactor>1</BFactor><GlassShare>0.74</GlassShare><SolarHeatTransmittance>0.51</SolarHeatTransmittance><SolarScreening>1</SolarScreening><OuterWallID>0</OuterWallID><Shade><ShortText>Standard anvendelseskode 110, 120 og 130 iht. HB2017</ShortText><Horizon>20</Horizon><Eaves>20</Eaves><Left>20</Left><Right>20</Right><WindowHole>10</WindowHole></Shade><DimensioningOuterTemperature>-12</DimensioningOuterTemperature><DimensioningInnerTemperature>20</DimensioningInnerTemperature><IsInMostSunBurdenedRoom>false</IsInMostSunBurdenedRoom></Window></BuildingUnit></Proposal></Proposals></Status><Status ID="9"><ShortText>Flerfagsvindue med gående rammer - 2 lags termorude kold kant</ShortText><LongText>Oplukkelige vinduer med flere fag. Vinduerne er monteret med tolags termorude.</LongText><BIClassification>1-3-1-0</BIClassification><BuildingUnit><Window xmlns="http://www.ens.dk/BuildingUnits"><NumberOfWindows>1</NumberOfWindows><Orientation>104</Orientation><Inclination>90</Inclination><Area>0.94</Area><UValue>2.7</UValue><BFactor>1</BFactor><GlassShare>0.57</GlassShare><SolarHeatTransmittance>0.75</SolarHeatTransmittance><SolarScreening>1</SolarScreening><OuterWallID>0</OuterWallID><Shade><ShortText>Standard anvendelseskode 110, 120 og 130 iht. HB2017</ShortText><Horizon>20</Horizon><Eaves>20</Eaves><Left>20</Left><Right>20</Right><WindowHole>10</WindowHole></Shade><DimensioningOuterTemperature>-12</DimensioningOuterTemperature><DimensioningInnerTemperature>20</DimensioningInnerTemperature><IsInMostSunBurdenedRoom>false</IsInMostSunBurdenedRoom></Window></BuildingUnit><Proposals><Proposal ID="6"><ShortText>Udskiftning af eksisterende flerfagsvinduer</ShortText><LongText>Eksisterende flerfagsvinduer foreslås udskiftet til nye vinduer med energiruder, energiklasse A.</LongText><LifeTime>30</LifeTime><Investment>6204</Investment><ProposeToTearDown>false</ProposeToTearDown><BIClassification>1-3-1-0</BIClassification><BuildingUnit><Window xmlns="http://www.ens.dk/BuildingUnits"><NumberOfWindows>1</NumberOfWindows><Orientation>104</Orientation><Inclination>90</Inclination><Area>0.94</Area><UValue>0.8</UValue><BFactor>1</BFactor><GlassShare>0.74</GlassShare><SolarHeatTransmittance>0.51</SolarHeatTransmittance><SolarScreening>1</SolarScreening><OuterWallID>0</OuterWallID><Shade><ShortText>Standard anvendelseskode 110, 120 og 130 iht. HB2017</ShortText><Horizon>20</Horizon><Eaves>20</Eaves><Left>20</Left><Right>20</Right><WindowHole>10</WindowHole></Shade><DimensioningOuterTemperature>-12</DimensioningOuterTemperature><DimensioningInnerTemperature>20</DimensioningInnerTemperature><IsInMostSunBurdenedRoom>false</IsInMostSunBurdenedRoom></Window></BuildingUnit></Proposal></Proposals></Status><Status ID="10"><ShortText>Flerfagsvindue med gående rammer - 2 lags termorude kold kant</ShortText><LongText>Oplukkelige vinduer med flere fag. Vinduerne er monteret med tolags termorude.</LongText><BIClassification>1-3-1-0</BIClassification><BuildingUnit><Window xmlns="http://www.ens.dk/BuildingUnits"><NumberOfWindows>2</NumberOfWindows><Orientation>104</Orientation><Inclination>90</Inclination><Area>2.17</Area><UValue>2.7</UValue><BFactor>1</BFactor><GlassShare>0.57</GlassShare><SolarHeatTransmittance>0.75</SolarHeatTransmittance><SolarScreening>1</SolarScreening><OuterWallID>0</OuterWallID><Shade><ShortText>Standard anvendelseskode 110, 120 og 130 iht. HB2017</ShortText><Horizon>20</Horizon><Eaves>20</Eaves><Left>20</Left><Right>20</Right><WindowHole>10</WindowHole></Shade><DimensioningOuterTemperature>-12</DimensioningOuterTemperature><DimensioningInnerTemperature>20</DimensioningInnerTemperature><IsInMostSunBurdenedRoom>false</IsInMostSunBurdenedRoom></Window></BuildingUnit><Proposals><Proposal ID="7"><ShortText>Udskiftning af eksisterende flerfagsvinduer</ShortText><LongText>Eksisterende flerfagsvinduer foreslås udskiftet til nye vinduer med energiruder, energiklasse A.</LongText><LifeTime>30</LifeTime><Investment>28644</Investment><ProposeToTearDown>false</ProposeToTearDown><BIClassification>1-3-1-0</BIClassification><BuildingUnit><Window xmlns="http://www.ens.dk/BuildingUnits"><NumberOfWindows>2</NumberOfWindows><Orientation>104</Orientation><Inclination>90</Inclination><Area>2.17</Area><UValue>0.8</UValue><BFactor>1</BFactor><GlassShare>0.74</GlassShare><SolarHeatTransmittance>0.51</SolarHeatTransmittance><SolarScreening>1</SolarScreening><OuterWallID>0</OuterWallID><Shade><ShortText>Standard anvendelseskode 110, 120 og 130 iht. HB2017</ShortText><Horizon>20</Horizon><Eaves>20</Eaves><Left>20</Left><Right>20</Right><WindowHole>10</WindowHole></Shade><DimensioningOuterTemperature>-12</DimensioningOuterTemperature><DimensioningInnerTemperature>20</DimensioningInnerTemperature><IsInMostSunBurdenedRoom>false</IsInMostSunBurdenedRoom></Window></BuildingUnit></Proposal></Proposals></Status><Status ID="11"><ShortText>Flerfagsvindue med gående rammer - 2 lags termorude kold kant</ShortText><LongText>Oplukkelige vinduer med flere fag. Vinduerne er monteret med tolags termorude.</LongText><BIClassification>1-3-1-0</BIClassification><BuildingUnit><Window xmlns="http://www.ens.dk/BuildingUnits"><NumberOfWindows>1</NumberOfWindows><Orientation>13</Orientation><Inclination>90</Inclination><Area>0.79</Area><UValue>2.7</UValue><BFactor>1</BFactor><GlassShare>0.57</GlassShare><SolarHeatTransmittance>0.75</SolarHeatTransmittance><SolarScreening>1</SolarScreening><OuterWallID>0</OuterWallID><Shade><ShortText>Standard anvendelseskode 110, 120 og 130 iht. HB2017</ShortText><Horizon>20</Horizon><Eaves>20</Eaves><Left>20</Left><Right>20</Right><WindowHole>10</WindowHole></Shade><DimensioningOuterTemperature>-12</DimensioningOuterTemperature><DimensioningInnerTemperature>20</DimensioningInnerTemperature><IsInMostSunBurdenedRoom>false</IsInMostSunBurdenedRoom></Window></BuildingUnit><Proposals><Proposal ID="8"><ShortText>Udskiftning af eksisterende flerfagsvinduer</ShortText><LongText>Eksisterende flerfagsvinduer foreslås udskiftet til nye vinduer med energiruder, energiklasse A.</LongText><LifeTime>30</LifeTime><Investment>5214</Investment><ProposeToTearDown>false</ProposeToTearDown><BIClassification>1-3-1-0</BIClassification><BuildingUnit><Window xmlns="http://www.ens.dk/BuildingUnits"><NumberOfWindows>1</NumberOfWindows><Orientation>13</Orientation><Inclination>90</Inclination><Area>0.79</Area><UValue>0.8</UValue><BFactor>1</BFactor><GlassShare>0.74</GlassShare><SolarHeatTransmittance>0.51</SolarHeatTransmittance><SolarScreening>1</SolarScreening><OuterWallID>0</OuterWallID><Shade><ShortText>Standard anvendelseskode 110, 120 og 130 iht. HB2017</ShortText><Horizon>20</Horizon><Eaves>20</Eaves><Left>20</Left><Right>20</Right><WindowHole>10</WindowHole></Shade><DimensioningOuterTemperature>-12</DimensioningOuterTemperature><DimensioningInnerTemperature>20</DimensioningInnerTemperature><IsInMostSunBurdenedRoom>false</IsInMostSunBurdenedRoom></Window></BuildingUnit></Proposal></Proposals></Status><Status ID="12"><ShortText>Linjetab: Vinduer og døre - HB2023</ShortText><LongText /><BIClassification>1-3-4-0</BIClassification><BuildingUnit><LinearThermalTransmittance xmlns="http://www.ens.dk/BuildingUnits"><Length>38.91</Length><HeatLoss>0.17</HeatLoss><BFactor>1</BFactor><DimensioningOuterTemperature>-12</DimensioningOuterTemperature><DimensioningInnerTemperature>20</DimensioningInnerTemperature></LinearThermalTransmittance></BuildingUnit><Proposals /></Status><Status ID="13"><ShortText>Linjetab: Fundament - HB2023</ShortText><LongText /><BIClassification>1-4-5-0</BIClassification><BuildingUnit><LinearThermalTransmittance xmlns="http://www.ens.dk/BuildingUnits"><Length>41.98</Length><HeatLoss>0.7</HeatLoss><BFactor>1.3</BFactor><DimensioningOuterTemperature>-12</DimensioningOuterTemperature><DimensioningInnerTemperature>20</DimensioningInnerTemperature></LinearThermalTransmittance></BuildingUnit><Proposals /></Status><Status ID="14"><ShortText>Grundfos UPM3 15-70 130/25-70 130/25-70 180 - 52 W</ShortText><LongText>Varmeanlægget er forsynet med en varmefordelingspumpe af fabrikat Grundfos type UPM3 15-70 130/25-70 130/25-70 180 - 52 W med en nominel effekt på 52 W. Pumpen er placeret i teknikrummet og er fra perioden 2022. </LongText><BIClassification>2-2-3-0</BIClassification><BuildingUnit><HeatDistributionPump xmlns="http://www.ens.dk/BuildingUnits"><NominalEffect>52</NominalEffect><ReductionFactor>0.3</ReductionFactor><NumberOfPumps>1</NumberOfPumps><Type>Season</Type></HeatDistributionPump></BuildingUnit><Proposals /></Status><Status ID="15"><ShortText>Gulvvarme - 2-streng iht. HB2023</ShortText><LongText>Den primære opvarmning af ejendommen sker via gulvvarme i opvarmede rum. Til hvert rum er fremført gulvvarmeslanger placeret i gulv. Rør er tilsluttet fordelerrør.</LongText><BIClassification>2-2-1-0</BIClassification><BuildingUnit><HeatDistributionSystem xmlns="http://www.ens.dk/BuildingUnits"><SupplyPipeTemperature>40</SupplyPipeTemperature><ReturnPipeTemperature>30</ReturnPipeTemperature><TypeOfSystem>Dual</TypeOfSystem></HeatDistributionSystem></BuildingUnit><Proposals /></Status><Status ID="16"><ShortText>El til varmepumpe</ShortText><LongText>Ejendommen opvarmes med varmepumpe.</LongText><BIClassification>2-1-1-0</BIClassification><BuildingUnit><ElectricHeat xmlns="http://www.ens.dk/BuildingUnits"><IsPrimary>true</IsPrimary><Fuel><Material xmlns="http://www.ens.dk/Globals">Electricity</Material><Unit xmlns="http://www.ens.dk/Globals">kWh</Unit><EnergyPerUnit xmlns="http://www.ens.dk/Globals">1</EnergyPerUnit><CO2PerUnit xmlns="http://www.ens.dk/Globals">197</CO2PerUnit></Fuel><FuelPrice><CostPerUnit xmlns="http://www.ens.dk/Globals">1.63</CostPerUnit><FixedCostPerYear xmlns="http://www.ens.dk/Globals">0</FixedCostPerYear><SupplierCompanyName xmlns="http://www.ens.dk/Globals" /></FuelPrice></ElectricHeat></BuildingUnit><Proposals /></Status><Status ID="17"><ShortText>Internt varmetilskud for enfamiliebyggeri</ShortText><LongText>Internt varmetilskud for enfamiliebyggeri.</LongText><BIClassification>1-6-1-0</BIClassification><BuildingUnit><InternalHeatContribution xmlns="http://www.ens.dk/BuildingUnits"><Area>100</Area><PowerFromPersons>1.5</PowerFromPersons><PowerFromDevicesInUsageHours>3.5</PowerFromDevicesInUsageHours><PowerFromDevicesOutsideUsageHours>0</PowerFromDevicesOutsideUsageHours></InternalHeatContribution></BuildingUnit><Proposals /></Status><Status ID="18"><ShortText>Bolig - Naturlig - tæt 0,3 l/s m²</ShortText><LongText>Der er naturlig ventilation i hele ejendommen. Ejendommen er normal tæt, da konstruktionssamlinger og fuger ved vindues- og døråbninger, samt tætningslister i vinduer og udvendige døre fremstår i god stand.</LongText><BIClassification>1-5-1-0</BIClassification><BuildingUnit><Ventilation xmlns="http://www.ens.dk/BuildingUnits"><Area>100</Area><UsageFactor>1</UsageFactor><NaturalVentilationWinter>0.3</NaturalVentilationWinter><NaturalVentilationSummer>2.4</NaturalVentilationSummer><NaturalVentilationSummerOutsideUsageHours>0</NaturalVentilationSummerOutsideUsageHours><MechanicalVentilationWinter>0</MechanicalVentilationWinter><MechanicalVentilationSummer>0</MechanicalVentilationSummer><MechanicalVentilationSummerOutsideUsageHours>0</MechanicalVentilationSummerOutsideUsageHours><InfiltrationOutsideUsageHours>0</InfiltrationOutsideUsageHours><TemperatureEfficiency>0</TemperatureEfficiency><InjectionTemperature>0</InjectionTemperature><SpecialPowerUsage>0</SpecialPowerUsage><HasHeatCoils>false</HasHeatCoils></Ventilation></BuildingUnit><Proposals /></Status><Status ID="19"><ShortText>Enfamiliehus - standard varmtvandforbrug</ShortText><LongText>I beregningen er der indregnet et varmtvandsforbrug på 250 liter pr. m² opvarmet etageareal pr. år.</LongText><BIClassification>3-1-1-0</BIClassification><BuildingUnit><HotWaterConsumption xmlns="http://www.ens.dk/BuildingUnits"><AverageConsumption>250</AverageConsumption><Temperature>55</Temperature></HotWaterConsumption></BuildingUnit><Proposals /></Status><Status ID="20"><ShortText>VVB er integreret i kedel</ShortText><LongText>Varmt brugsvand produceres via varmtvandsbeholder der er integreret i kedel.</LongText><BIClassification>3-1-5-0</BIClassification><BuildingUnit><HotWaterTank xmlns="http://www.ens.dk/BuildingUnits"><NumberOfTanks>1</NumberOfTanks><ShareOfHotWaterConsumption>1</ShareOfHotWaterConsumption><Volume>0</Volume><SupplyTemperature>65</SupplyTemperature><ElectricalSupport>None</ElectricalSupport><HasHeatingCoil>false</HasHeatingCoil><HeatLoss>0</HeatLoss><BFactor>0</BFactor></HotWaterTank></BuildingUnit><Proposals /></Status><Status ID="21"><ShortText>Luft/vand - Vølund F2026-10</ShortText><LongText>Bygningen opvarmes med en luft/vand-varmepumpe af mærket Vølund F2025-10. Selve indedelen er placeret i teknikrum. Indregning af pumpens ydelser er udført iht. producentens anvisninger.</LongText><BIClassification>2-1-5-0</BIClassification><BuildingUnit><HeatPump xmlns="http://www.ens.dk/BuildingUnits"><Type>Combined</Type><ShareOfFloorArea>1</ShareOfFloorArea><RoomHeating><NominalEffect>9.8</NominalEffect><NominalCOP>3.1</NominalCOP><RelativeCOP>0.94</RelativeCOP><ColdSideTestTemperature>7</ColdSideTestTemperature><WarmSideTestTemperature>45</WarmSideTestTemperature><SpecialAuxiliaryToolPowerUsage>1</SpecialAuxiliaryToolPowerUsage><StandbyPowerUsage>5</StandbyPowerUsage><TemperatureEfficiency>0</TemperatureEfficiency><DimensioningAirSupplyTemperature>0</DimensioningAirSupplyTemperature><AirFlowRequirement>0</AirFlowRequirement><TempDiffExchangerColdSideTemperatureForOtherSource>0</TempDiffExchangerColdSideTemperatureForOtherSource><ColdMedium>OuterAir</ColdMedium><WarmMedium>HeatingSystem</WarmMedium></RoomHeating><HotWater><NominalEffect>9.8</NominalEffect><NominalCOP>3.1</NominalCOP><ColdSideTestTemperature>7</ColdSideTestTemperature><WarmSideTestTemperature>45</WarmSideTestTemperature><SpecialAuxiliaryToolPowerUsage>1</SpecialAuxiliaryToolPowerUsage><StandbyPowerUsage>0</StandbyPowerUsage><TemperatureEfficiency>0</TemperatureEfficiency><AirFlowRequirement>0</AirFlowRequirement><TempDiffExchangerColdSideTemperatureForOtherSource>0</TempDiffExchangerColdSideTemperatureForOtherSource><ColdMedium>OuterAir</ColdMedium></HotWater></HeatPump></BuildingUnit><Proposals /></Status><Status ID="22"><ShortText>Ingen solcelle</ShortText><LongText>Der er ingen solceller på bygningen.</LongText><BIClassification>4-1-3-0</BIClassification><Proposals><Proposal ID="9"><ShortText>Montage af nye solceller</ShortText><LongText>Montering af solceller på tagflade mod syd . Det anbefales at der monteres solceller af typen Monokrystallinske silicium med et areal på ca. 20 m². Det forslåede anlæg har en effekt på 4,2 kW. For at opnå optimal virkningsgrad kan det være nødvendigt at beskære eventuelle trækroner, så der ikke opstår skyggevirkning på solcellerne. Det bør undersøges, om den eksisterende tagkonstruktion er egnet til den ekstra vægt fra solcellerne. En eventuel udgift til dette er ikke medtaget i forslagets økonomi. I det foreslåede anlæg er der ikke  taget højde for eventuelle restriktioner i forhold til Planlovsbestemmelser herunder lokalplan m.v. 
Modsat solvarme og varmepumpe, supplerer solceller strømforsyningen og ikke varmeforsyningen, hvis der ikke anvendes el til opvarmning af bygningen.</LongText><LifeTime>20</LifeTime><Investment>40800</Investment><ProposeToTearDown>false</ProposeToTearDown><BIClassification>4-1-3-0</BIClassification><BuildingUnit><SolarCell xmlns="http://www.ens.dk/BuildingUnits"><Orientation>180</Orientation><Area>20.4</Area><Inclination>45</Inclination><HorizonCutOff>0</HorizonCutOff><ShadeLeft>0</ShadeLeft><ShadeRight>0</ShadeRight><PeakPower>0.206</PeakPower><Efficiency>0.85</Efficiency></SolarCell></BuildingUnit></Proposal></Proposals></Status><Status ID="23"><ShortText>Intet solvarmeanlæg - Intet forslag</ShortText><LongText>Der er ikke stillet forslag til solvarmeanlæg, da dette, med bygningens eksisterende varmeanlæg og den dertilhørende energipris, ikke vil kunne medføre et fornuftigt og rentabelt forslag.</LongText><BIClassification>2-1-6-0</BIClassification><Proposals /></Status></Statuses></Zone></Zones></Building></Buildings><Images></Images></Label></InputData><ResultData xmlns="http://www.ens.dk/ResultData"><LabelResults><Status><EnergyLabelClassification>C</EnergyLabelClassification><FuelConsumption><Fuel><Material xmlns="http://www.ens.dk/Globals">Electricity</Material><Unit xmlns="http://www.ens.dk/Globals">kWh</Unit><EnergyPerUnit xmlns="http://www.ens.dk/Globals">1</EnergyPerUnit><CO2PerUnit xmlns="http://www.ens.dk/Globals">197</CO2PerUnit></Fuel><FuelPrice><CostPerUnit xmlns="http://www.ens.dk/Globals">1.63</CostPerUnit><FixedCostPerYear xmlns="http://www.ens.dk/Globals">0</FixedCostPerYear><SupplierCompanyName xmlns="http://www.ens.dk/Globals" /></FuelPrice><FuelConsumption>5441.00</FuelConsumption><IsForHeating>true</IsForHeating></FuelConsumption><FuelConsumption><Fuel><Material xmlns="http://www.ens.dk/Globals">Electricity</Material><Unit xmlns="http://www.ens.dk/Globals">kWh</Unit><EnergyPerUnit xmlns="http://www.ens.dk/Globals">1</EnergyPerUnit><CO2PerUnit xmlns="http://www.ens.dk/Globals">197</CO2PerUnit></Fuel><FuelPrice><CostPerUnit xmlns="http://www.ens.dk/Globals">1.63</CostPerUnit><FixedCostPerYear xmlns="http://www.ens.dk/Globals">0</FixedCostPerYear><SupplierCompanyName xmlns="http://www.ens.dk/Globals" /></FuelPrice><FuelConsumption>3209.0</FuelConsumption><IsForHeating>false</IsForHeating></FuelConsumption></Status><ResultForAllProfitableProposals><EnergyLabelClassification>B</EnergyLabelClassification><FuelConsumption><Fuel><Material xmlns="http://www.ens.dk/Globals">Electricity</Material><Unit xmlns="http://www.ens.dk/Globals">kWh</Unit><EnergyPerUnit xmlns="http://www.ens.dk/Globals">1</EnergyPerUnit><CO2PerUnit xmlns="http://www.ens.dk/Globals">197</CO2PerUnit></Fuel><FuelPrice><CostPerUnit xmlns="http://www.ens.dk/Globals">1.63</CostPerUnit><FixedCostPerYear xmlns="http://www.ens.dk/Globals">0</FixedCostPerYear><SupplierCompanyName xmlns="http://www.ens.dk/Globals" /></FuelPrice><FuelConsumption>4509.3752737187199580034303233</FuelConsumption><IsForHeating>true</IsForHeating></FuelConsumption><FuelConsumption><Fuel><Material xmlns="http://www.ens.dk/Globals">Electricity</Material><Unit xmlns="http://www.ens.dk/Globals">kWh</Unit><EnergyPerUnit xmlns="http://www.ens.dk/Globals">1</EnergyPerUnit><CO2PerUnit xmlns="http://www.ens.dk/Globals">197</CO2PerUnit></Fuel><FuelPrice><CostPerUnit xmlns="http://www.ens.dk/Globals">1.63</CostPerUnit><FixedCostPerYear xmlns="http://www.ens.dk/Globals">0</FixedCostPerYear><SupplierCompanyName xmlns="http://www.ens.dk/Globals" /></FuelPrice><FuelConsumption>2426.8847379767040580090548639</FuelConsumption><IsForHeating>false</IsForHeating></FuelConsumption></ResultForAllProfitableProposals><ResultForAllProposals><EnergyLabelClassification>A2010</EnergyLabelClassification><FuelConsumption><Fuel><Material xmlns="http://www.ens.dk/Globals">Electricity</Material><Unit xmlns="http://www.ens.dk/Globals">kWh</Unit><EnergyPerUnit xmlns="http://www.ens.dk/Globals">1</EnergyPerUnit><CO2PerUnit xmlns="http://www.ens.dk/Globals">197</CO2PerUnit></Fuel><FuelPrice><CostPerUnit xmlns="http://www.ens.dk/Globals">1.63</CostPerUnit><FixedCostPerYear xmlns="http://www.ens.dk/Globals">0</FixedCostPerYear><SupplierCompanyName xmlns="http://www.ens.dk/Globals" /></FuelPrice><FuelConsumption>3523.4458523907133145793073024</FuelConsumption><IsForHeating>true</IsForHeating></FuelConsumption><FuelConsumption><Fuel><Material xmlns="http://www.ens.dk/Globals">Electricity</Material><Unit xmlns="http://www.ens.dk/Globals">kWh</Unit><EnergyPerUnit xmlns="http://www.ens.dk/Globals">1</EnergyPerUnit><CO2PerUnit xmlns="http://www.ens.dk/Globals">197</CO2PerUnit></Fuel><FuelPrice><CostPerUnit xmlns="http://www.ens.dk/Globals">1.63</CostPerUnit><FixedCostPerYear xmlns="http://www.ens.dk/Globals">0</FixedCostPerYear><SupplierCompanyName xmlns="http://www.ens.dk/Globals" /></FuelPrice><FuelConsumption>2378.7465008623763609171084233</FuelConsumption><IsForHeating>false</IsForHeating></FuelConsumption></ResultForAllProposals><ResultsForEachProposalGroup><ProposalGroupResult ProposalGroupID="0"><Profitability>0.6193245952197378565921356978</Profitability><Category>ProfitableWhenRenovating</Category><Investment>32425</Investment><InvestmentLifetime>40</InvestmentLifetime><FuelSavings><FuelSaving><Fuel><Material xmlns="http://www.ens.dk/Globals">Electricity</Material><Unit xmlns="http://www.ens.dk/Globals">kWh</Unit><EnergyPerUnit xmlns="http://www.ens.dk/Globals">1</EnergyPerUnit><CO2PerUnit xmlns="http://www.ens.dk/Globals">197</CO2PerUnit></Fuel><FuelPrice><CostPerUnit xmlns="http://www.ens.dk/Globals">1.63</CostPerUnit><FixedCostPerYear xmlns="http://www.ens.dk/Globals">0</FixedCostPerYear><SupplierCompanyName xmlns="http://www.ens.dk/Globals" /></FuelPrice><FuelSaved>308.00</FuelSaved></FuelSaving></FuelSavings></ProposalGroupResult><ProposalGroupResult ProposalGroupID="1"><Profitability>0.3206004140786749482401656315</Profitability><Category>ProfitableWhenRenovating</Category><Investment>26082</Investment><InvestmentLifetime>30</InvestmentLifetime><FuelSavings><FuelSaving><Fuel><Material xmlns="http://www.ens.dk/Globals">Electricity</Material><Unit xmlns="http://www.ens.dk/Globals">kWh</Unit><EnergyPerUnit xmlns="http://www.ens.dk/Globals">1</EnergyPerUnit><CO2PerUnit xmlns="http://www.ens.dk/Globals">197</CO2PerUnit></Fuel><FuelPrice><CostPerUnit xmlns="http://www.ens.dk/Globals">1.63</CostPerUnit><FixedCostPerYear xmlns="http://www.ens.dk/Globals">0</FixedCostPerYear><SupplierCompanyName xmlns="http://www.ens.dk/Globals" /></FuelPrice><FuelSaved>171.00</FuelSaved></FuelSaving></FuelSavings></ProposalGroupResult><ProposalGroupResult ProposalGroupID="2"><Profitability>0.4020484949832775919732441472</Profitability><Category>ProfitableWhenRenovating</Category><Investment>78936</Investment><InvestmentLifetime>30</InvestmentLifetime><FuelSavings><FuelSaving><Fuel><Material xmlns="http://www.ens.dk/Globals">Electricity</Material><Unit xmlns="http://www.ens.dk/Globals">kWh</Unit><EnergyPerUnit xmlns="http://www.ens.dk/Globals">1</EnergyPerUnit><CO2PerUnit xmlns="http://www.ens.dk/Globals">197</CO2PerUnit></Fuel><FuelPrice><CostPerUnit xmlns="http://www.ens.dk/Globals">1.63</CostPerUnit><FixedCostPerYear xmlns="http://www.ens.dk/Globals">0</FixedCostPerYear><SupplierCompanyName xmlns="http://www.ens.dk/Globals" /></FuelPrice><FuelSaved>649.00</FuelSaved></FuelSaving></FuelSavings></ProposalGroupResult><ProposalGroupResult ProposalGroupID="3"><Profitability>1.5744045013190061060301578053</Profitability><Category>Profitable</Category><Investment>40800</Investment><InvestmentLifetime>20</InvestmentLifetime><FuelSavings><FuelSaving><Fuel><Material xmlns="http://www.ens.dk/Globals">Electricity</Material><Unit xmlns="http://www.ens.dk/Globals">kWh</Unit><EnergyPerUnit xmlns="http://www.ens.dk/Globals">1</EnergyPerUnit><CO2PerUnit xmlns="http://www.ens.dk/Globals">197</CO2PerUnit></Fuel><FuelPrice><CostPerUnit xmlns="http://www.ens.dk/Globals">1.63</CostPerUnit><FixedCostPerYear xmlns="http://www.ens.dk/Globals">0</FixedCostPerYear><SupplierCompanyName xmlns="http://www.ens.dk/Globals" /></FuelPrice><FuelSaved>931.6247262812800419965696767</FuelSaved></FuelSaving><FuelSaving><Fuel><Material xmlns="http://www.ens.dk/Globals">Electricity</Material><Unit xmlns="http://www.ens.dk/Globals">kWh</Unit><EnergyPerUnit xmlns="http://www.ens.dk/Globals">1</EnergyPerUnit><CO2PerUnit xmlns="http://www.ens.dk/Globals">197</CO2PerUnit></Fuel><FuelPrice><CostPerUnit xmlns="http://www.ens.dk/Globals">1.63</CostPerUnit><FixedCostPerYear xmlns="http://www.ens.dk/Globals">0</FixedCostPerYear><SupplierCompanyName xmlns="http://www.ens.dk/Globals" /></FuelPrice><FuelSaved>782.1152620232959419909451361</FuelSaved></FuelSaving><FuelSaving><Fuel><Material xmlns="http://www.ens.dk/Globals">Electricity</Material><Unit xmlns="http://www.ens.dk/Globals">kWh</Unit><EnergyPerUnit xmlns="http://www.ens.dk/Globals">1</EnergyPerUnit><CO2PerUnit xmlns="http://www.ens.dk/Globals">197</CO2PerUnit></Fuel><FuelPrice><CostPerUnit xmlns="http://www.ens.dk/Globals">0.15</CostPerUnit><FixedCostPerYear xmlns="http://www.ens.dk/Globals">0</FixedCostPerYear><SupplierCompanyName xmlns="http://www.ens.dk/Globals" /></FuelPrice><FuelSaved>2789.2600116954240160124851872</FuelSaved></FuelSaving></FuelSavings></ProposalGroupResult></ResultsForEachProposalGroup><Apartments /></LabelResults><BuildingResults><BuildingResult BuildingID="0"><Status><EnergyLabelClassification>C</EnergyLabelClassification><FuelConsumption><Fuel><Material xmlns="http://www.ens.dk/Globals">Electricity</Material><Unit xmlns="http://www.ens.dk/Globals">kWh</Unit><EnergyPerUnit xmlns="http://www.ens.dk/Globals">1</EnergyPerUnit><CO2PerUnit xmlns="http://www.ens.dk/Globals">197</CO2PerUnit></Fuel><FuelPrice><CostPerUnit xmlns="http://www.ens.dk/Globals">1.63</CostPerUnit><FixedCostPerYear xmlns="http://www.ens.dk/Globals">0</FixedCostPerYear><SupplierCompanyName xmlns="http://www.ens.dk/Globals" /></FuelPrice><FuelConsumption>5441.00</FuelConsumption><IsForHeating>true</IsForHeating></FuelConsumption><FuelConsumption><Fuel><Material xmlns="http://www.ens.dk/Globals">Electricity</Material><Unit xmlns="http://www.ens.dk/Globals">kWh</Unit><EnergyPerUnit xmlns="http://www.ens.dk/Globals">1</EnergyPerUnit><CO2PerUnit xmlns="http://www.ens.dk/Globals">197</CO2PerUnit></Fuel><FuelPrice><CostPerUnit xmlns="http://www.ens.dk/Globals">1.63</CostPerUnit><FixedCostPerYear xmlns="http://www.ens.dk/Globals">0</FixedCostPerYear><SupplierCompanyName xmlns="http://www.ens.dk/Globals" /></FuelPrice><FuelConsumption>3209.0</FuelConsumption><IsForHeating>false</IsForHeating></FuelConsumption></Status><ResultForAllProfitableProposals><EnergyLabelClassification>B</EnergyLabelClassification><FuelConsumption><Fuel><Material xmlns="http://www.ens.dk/Globals">Electricity</Material><Unit xmlns="http://www.ens.dk/Globals">kWh</Unit><EnergyPerUnit xmlns="http://www.ens.dk/Globals">1</EnergyPerUnit><CO2PerUnit xmlns="http://www.ens.dk/Globals">197</CO2PerUnit></Fuel><FuelPrice><CostPerUnit xmlns="http://www.ens.dk/Globals">1.63</CostPerUnit><FixedCostPerYear xmlns="http://www.ens.dk/Globals">0</FixedCostPerYear><SupplierCompanyName xmlns="http://www.ens.dk/Globals" /></FuelPrice><FuelConsumption>4509.3752737187199580034303233</FuelConsumption><IsForHeating>true</IsForHeating></FuelConsumption><FuelConsumption><Fuel><Material xmlns="http://www.ens.dk/Globals">Electricity</Material><Unit xmlns="http://www.ens.dk/Globals">kWh</Unit><EnergyPerUnit xmlns="http://www.ens.dk/Globals">1</EnergyPerUnit><CO2PerUnit xmlns="http://www.ens.dk/Globals">197</CO2PerUnit></Fuel><FuelPrice><CostPerUnit xmlns="http://www.ens.dk/Globals">1.63</CostPerUnit><FixedCostPerYear xmlns="http://www.ens.dk/Globals">0</FixedCostPerYear><SupplierCompanyName xmlns="http://www.ens.dk/Globals" /></FuelPrice><FuelConsumption>2426.8847379767040580090548639</FuelConsumption><IsForHeating>false</IsForHeating></FuelConsumption></ResultForAllProfitableProposals><ResultForAllProposals><EnergyLabelClassification>A2010</EnergyLabelClassification><FuelConsumption><Fuel><Material xmlns="http://www.ens.dk/Globals">Electricity</Material><Unit xmlns="http://www.ens.dk/Globals">kWh</Unit><EnergyPerUnit xmlns="http://www.ens.dk/Globals">1</EnergyPerUnit><CO2PerUnit xmlns="http://www.ens.dk/Globals">197</CO2PerUnit></Fuel><FuelPrice><CostPerUnit xmlns="http://www.ens.dk/Globals">1.63</CostPerUnit><FixedCostPerYear xmlns="http://www.ens.dk/Globals">0</FixedCostPerYear><SupplierCompanyName xmlns="http://www.ens.dk/Globals" /></FuelPrice><FuelConsumption>3523.4458523907133145793073024</FuelConsumption><IsForHeating>true</IsForHeating></FuelConsumption><FuelConsumption><Fuel><Material xmlns="http://www.ens.dk/Globals">Electricity</Material><Unit xmlns="http://www.ens.dk/Globals">kWh</Unit><EnergyPerUnit xmlns="http://www.ens.dk/Globals">1</EnergyPerUnit><CO2PerUnit xmlns="http://www.ens.dk/Globals">197</CO2PerUnit></Fuel><FuelPrice><CostPerUnit xmlns="http://www.ens.dk/Globals">1.63</CostPerUnit><FixedCostPerYear xmlns="http://www.ens.dk/Globals">0</FixedCostPerYear><SupplierCompanyName xmlns="http://www.ens.dk/Globals" /></FuelPrice><FuelConsumption>2378.7465008623763609171084233</FuelConsumption><IsForHeating>false</IsForHeating></FuelConsumption></ResultForAllProposals><AdjustedReportedConsumptions /><AdjustedLoggedConsumptions></AdjustedLoggedConsumptions></BuildingResult></BuildingResults><ZoneResults><ZoneResult ZoneID="0"><Status><EnergyLabelClassification>C</EnergyLabelClassification><FuelConsumption><Fuel><Material xmlns="http://www.ens.dk/Globals">Electricity</Material><Unit xmlns="http://www.ens.dk/Globals">kWh</Unit><EnergyPerUnit xmlns="http://www.ens.dk/Globals">1</EnergyPerUnit><CO2PerUnit xmlns="http://www.ens.dk/Globals">197</CO2PerUnit></Fuel><FuelPrice><CostPerUnit xmlns="http://www.ens.dk/Globals">1.63</CostPerUnit><FixedCostPerYear xmlns="http://www.ens.dk/Globals">0</FixedCostPerYear><SupplierCompanyName xmlns="http://www.ens.dk/Globals" /></FuelPrice><FuelConsumption>5441.00</FuelConsumption><IsForHeating>true</IsForHeating></FuelConsumption><FuelConsumption><Fuel><Material xmlns="http://www.ens.dk/Globals">Electricity</Material><Unit xmlns="http://www.ens.dk/Globals">kWh</Unit><EnergyPerUnit xmlns="http://www.ens.dk/Globals">1</EnergyPerUnit><CO2PerUnit xmlns="http://www.ens.dk/Globals">197</CO2PerUnit></Fuel><FuelPrice><CostPerUnit xmlns="http://www.ens.dk/Globals">1.63</CostPerUnit><FixedCostPerYear xmlns="http://www.ens.dk/Globals">0</FixedCostPerYear><SupplierCompanyName xmlns="http://www.ens.dk/Globals" /></FuelPrice><FuelConsumption>3209.0</FuelConsumption><IsForHeating>false</IsForHeating></FuelConsumption><CalculatedSolarCellUtilization><SolarCellShare>0</SolarCellShare><TotalUtilizationPercent>0</TotalUtilizationPercent></CalculatedSolarCellUtilization><CalculatedBe18Result><ResultFigures><HeatingRequirementForCentralHeating>0.00</HeatingRequirementForCentralHeating><HeatingRequirementForStoves>0.00</HeatingRequirementForStoves><HeatingRequirementForCentralHeatingDegreeDayIndependent>0.00</HeatingRequirementForCentralHeatingDegreeDayIndependent><ElectricityRequirementForHeating>5441.00</ElectricityRequirementForHeating><ElectricityRequirementForNonHeating>143.0</ElectricityRequirementForNonHeating><ElectricityRequirementForLighting>0.0</ElectricityRequirementForLighting><ElectricityRequirementForVentilation>0.0</ElectricityRequirementForVentilation><ElectricityRequirementForHeatPump>4129.0</ElectricityRequirementForHeatPump><ElectricityRequirementForPumps>99.0</ElectricityRequirementForPumps><HeatPumpHeatingTotalPerformance>12.85</HeatPumpHeatingTotalPerformance><SolarHeatingPlantHeatingTotalPerformance>0.00</SolarHeatingPlantHeatingTotalPerformance><SolarCellsTotalPerformance>0.0</SolarCellsTotalPerformance><WindMillsTotalPerformance>0.0</WindMillsTotalPerformance><FulfilmentHeatingHotWater>0.00</FulfilmentHeatingHotWater><FulfilmentElectricityHotWater>1.31</FulfilmentElectricityHotWater><BoilerEfficiency>0.0</BoilerEfficiency></ResultFigures><KeyFigures><TransmissionLossThroughEnvelopeExcludingWindowsAndDoors>42.5</TransmissionLossThroughEnvelopeExcludingWindowsAndDoors><RenovationClass2><EnergyFrameInBRNoAddition>40</EnergyFrameInBRNoAddition><AdditionToEnergyFrameDueToSpecialConditions>0</AdditionToEnergyFrameDueToSpecialConditions><TotalEnergyRequirement>106.115</TotalEnergyRequirement><ContributionToEnergyRequirementHeating>0.00</ContributionToEnergyRequirementHeating></RenovationClass2><RenovationClass1><EnergyFrameInBRNoAddition>40</EnergyFrameInBRNoAddition><AdditionToEnergyFrameDueToSpecialConditions>0</AdditionToEnergyFrameDueToSpecialConditions><TotalEnergyRequirement>106.115</TotalEnergyRequirement><ContributionToEnergyRequirementHeating>0.00</ContributionToEnergyRequirementHeating></RenovationClass1><EnergyFrame2018><EnergyFrameInBRNoAddition>40</EnergyFrameInBRNoAddition><AdditionToEnergyFrameDueToSpecialConditions>0</AdditionToEnergyFrameDueToSpecialConditions><TotalEnergyRequirement>106.115</TotalEnergyRequirement><ContributionToEnergyRequirementHeating>0.00</ContributionToEnergyRequirementHeating><ContributionToEnergyRequirementElectricity>106.115</ContributionToEnergyRequirementElectricity><ContributionToEnergyRequirementExcessTemperature>0.00</ContributionToEnergyRequirementExcessTemperature></EnergyFrame2018><LowEnergyFrame><EnergyFrameInBRNoAddition>27</EnergyFrameInBRNoAddition><AdditionToEnergyFrameDueToSpecialConditions>0</AdditionToEnergyFrameDueToSpecialConditions><TotalEnergyRequirement>106.115</TotalEnergyRequirement><ContributionToEnergyRequirementHeating>0.00</ContributionToEnergyRequirementHeating><ContributionToEnergyRequirementElectricity>106.115</ContributionToEnergyRequirementElectricity><ContributionToEnergyRequirementExcessTemperature>0.00</ContributionToEnergyRequirementExcessTemperature></LowEnergyFrame></KeyFigures></CalculatedBe18Result></Status><ResultForAllProfitableProposals><EnergyLabelClassification>B</EnergyLabelClassification><FuelConsumption><Fuel><Material xmlns="http://www.ens.dk/Globals">Electricity</Material><Unit xmlns="http://www.ens.dk/Globals">kWh</Unit><EnergyPerUnit xmlns="http://www.ens.dk/Globals">1</EnergyPerUnit><CO2PerUnit xmlns="http://www.ens.dk/Globals">197</CO2PerUnit></Fuel><FuelPrice><CostPerUnit xmlns="http://www.ens.dk/Globals">1.63</CostPerUnit><FixedCostPerYear xmlns="http://www.ens.dk/Globals">0</FixedCostPerYear><SupplierCompanyName xmlns="http://www.ens.dk/Globals" /></FuelPrice><FuelConsumption>4509.3752737187199580034303233</FuelConsumption><IsForHeating>true</IsForHeating></FuelConsumption><FuelConsumption><Fuel><Material xmlns="http://www.ens.dk/Globals">Electricity</Material><Unit xmlns="http://www.ens.dk/Globals">kWh</Unit><EnergyPerUnit xmlns="http://www.ens.dk/Globals">1</EnergyPerUnit><CO2PerUnit xmlns="http://www.ens.dk/Globals">197</CO2PerUnit></Fuel><FuelPrice><CostPerUnit xmlns="http://www.ens.dk/Globals">1.63</CostPerUnit><FixedCostPerYear xmlns="http://www.ens.dk/Globals">0</FixedCostPerYear><SupplierCompanyName xmlns="http://www.ens.dk/Globals" /></FuelPrice><FuelConsumption>2426.8847379767040580090548639</FuelConsumption><IsForHeating>false</IsForHeating></FuelConsumption><CalculatedSolarCellUtilization><SolarCellShare>0.5036349401632926965663795996</SolarCellShare><TotalUtilizationPercent>0.3834286480131635289568878515</TotalUtilizationPercent></CalculatedSolarCellUtilization><CalculatedBe18Result><ResultFigures><HeatingRequirementForCentralHeating>0.00</HeatingRequirementForCentralHeating><HeatingRequirementForStoves>0.00</HeatingRequirementForStoves><HeatingRequirementForCentralHeatingDegreeDayIndependent>0.00</HeatingRequirementForCentralHeatingDegreeDayIndependent><ElectricityRequirementForHeating>5441.00</ElectricityRequirementForHeating><ElectricityRequirementForNonHeating>143.0</ElectricityRequirementForNonHeating><ElectricityRequirementForLighting>0.0</ElectricityRequirementForLighting><ElectricityRequirementForVentilation>0.0</ElectricityRequirementForVentilation><ElectricityRequirementForHeatPump>4129.0</ElectricityRequirementForHeatPump><ElectricityRequirementForPumps>99.0</ElectricityRequirementForPumps><HeatPumpHeatingTotalPerformance>12.85</HeatPumpHeatingTotalPerformance><SolarHeatingPlantHeatingTotalPerformance>0.00</SolarHeatingPlantHeatingTotalPerformance><SolarCellsTotalPerformance>4503.0</SolarCellsTotalPerformance><WindMillsTotalPerformance>0.0</WindMillsTotalPerformance><FulfilmentHeatingHotWater>0.00</FulfilmentHeatingHotWater><FulfilmentElectricityHotWater>1.31</FulfilmentElectricityHotWater><BoilerEfficiency>0.0</BoilerEfficiency></ResultFigures><KeyFigures><TransmissionLossThroughEnvelopeExcludingWindowsAndDoors>42.5</TransmissionLossThroughEnvelopeExcludingWindowsAndDoors><RenovationClass2><EnergyFrameInBRNoAddition>40</EnergyFrameInBRNoAddition><AdditionToEnergyFrameDueToSpecialConditions>0</AdditionToEnergyFrameDueToSpecialConditions><TotalEnergyRequirement>81.11500000000000000000000000</TotalEnergyRequirement><ContributionToEnergyRequirementHeating>0.00</ContributionToEnergyRequirementHeating></RenovationClass2><RenovationClass1><EnergyFrameInBRNoAddition>40</EnergyFrameInBRNoAddition><AdditionToEnergyFrameDueToSpecialConditions>0</AdditionToEnergyFrameDueToSpecialConditions><TotalEnergyRequirement>81.11500000000000000000000000</TotalEnergyRequirement><ContributionToEnergyRequirementHeating>0.00</ContributionToEnergyRequirementHeating></RenovationClass1><EnergyFrame2018><EnergyFrameInBRNoAddition>40</EnergyFrameInBRNoAddition><AdditionToEnergyFrameDueToSpecialConditions>0</AdditionToEnergyFrameDueToSpecialConditions><TotalEnergyRequirement>81.11500000000000000000000000</TotalEnergyRequirement><ContributionToEnergyRequirementHeating>0.00</ContributionToEnergyRequirementHeating><ContributionToEnergyRequirementElectricity>81.11500000000000000000000000</ContributionToEnergyRequirementElectricity><ContributionToEnergyRequirementExcessTemperature>0.00</ContributionToEnergyRequirementExcessTemperature></EnergyFrame2018><LowEnergyFrame><EnergyFrameInBRNoAddition>27</EnergyFrameInBRNoAddition><AdditionToEnergyFrameDueToSpecialConditions>0</AdditionToEnergyFrameDueToSpecialConditions><TotalEnergyRequirement>81.11500000000000000000000000</TotalEnergyRequirement><ContributionToEnergyRequirementHeating>0.00</ContributionToEnergyRequirementHeating><ContributionToEnergyRequirementElectricity>81.11500000000000000000000000</ContributionToEnergyRequirementElectricity><ContributionToEnergyRequirementExcessTemperature>0.00</ContributionToEnergyRequirementExcessTemperature></LowEnergyFrame></KeyFigures></CalculatedBe18Result></ResultForAllProfitableProposals><ResultForAllProposals><EnergyLabelClassification>A2010</EnergyLabelClassification><FuelConsumption><Fuel><Material xmlns="http://www.ens.dk/Globals">Electricity</Material><Unit xmlns="http://www.ens.dk/Globals">kWh</Unit><EnergyPerUnit xmlns="http://www.ens.dk/Globals">1</EnergyPerUnit><CO2PerUnit xmlns="http://www.ens.dk/Globals">197</CO2PerUnit></Fuel><FuelPrice><CostPerUnit xmlns="http://www.ens.dk/Globals">1.63</CostPerUnit><FixedCostPerYear xmlns="http://www.ens.dk/Globals">0</FixedCostPerYear><SupplierCompanyName xmlns="http://www.ens.dk/Globals" /></FuelPrice><FuelConsumption>3523.4458523907133145793073024</FuelConsumption><IsForHeating>true</IsForHeating></FuelConsumption><FuelConsumption><Fuel><Material xmlns="http://www.ens.dk/Globals">Electricity</Material><Unit xmlns="http://www.ens.dk/Globals">kWh</Unit><EnergyPerUnit xmlns="http://www.ens.dk/Globals">1</EnergyPerUnit><CO2PerUnit xmlns="http://www.ens.dk/Globals">197</CO2PerUnit></Fuel><FuelPrice><CostPerUnit xmlns="http://www.ens.dk/Globals">1.63</CostPerUnit><FixedCostPerYear xmlns="http://www.ens.dk/Globals">0</FixedCostPerYear><SupplierCompanyName xmlns="http://www.ens.dk/Globals" /></FuelPrice><FuelConsumption>2378.7465008623763609171084233</FuelConsumption><IsForHeating>false</IsForHeating></FuelConsumption><CalculatedSolarCellUtilization><SolarCellShare>0.5760521939362926954074453115</SolarCellShare><TotalUtilizationPercent>0.3630578820832282350281167049</TotalUtilizationPercent></CalculatedSolarCellUtilization><CalculatedBe18Result><ResultFigures><HeatingRequirementForCentralHeating>0.00</HeatingRequirementForCentralHeating><HeatingRequirementForStoves>0.00</HeatingRequirementForStoves><HeatingRequirementForCentralHeatingDegreeDayIndependent>0.00</HeatingRequirementForCentralHeatingDegreeDayIndependent><ElectricityRequirementForHeating>4317.00</ElectricityRequirementForHeating><ElectricityRequirementForNonHeating>142.0</ElectricityRequirementForNonHeating><ElectricityRequirementForLighting>0.0</ElectricityRequirementForLighting><ElectricityRequirementForVentilation>0.0</ElectricityRequirementForVentilation><ElectricityRequirementForHeatPump>3005.0</ElectricityRequirementForHeatPump><ElectricityRequirementForPumps>98.0</ElectricityRequirementForPumps><HeatPumpHeatingTotalPerformance>9.28</HeatPumpHeatingTotalPerformance><SolarHeatingPlantHeatingTotalPerformance>0.00</SolarHeatingPlantHeatingTotalPerformance><SolarCellsTotalPerformance>4503.0</SolarCellsTotalPerformance><WindMillsTotalPerformance>0.0</WindMillsTotalPerformance><FulfilmentHeatingHotWater>0.00</FulfilmentHeatingHotWater><FulfilmentElectricityHotWater>1.31</FulfilmentElectricityHotWater><BoilerEfficiency>0.0</BoilerEfficiency></ResultFigures><KeyFigures><TransmissionLossThroughEnvelopeExcludingWindowsAndDoors>30.0</TransmissionLossThroughEnvelopeExcludingWindowsAndDoors><RenovationClass2><EnergyFrameInBRNoAddition>40</EnergyFrameInBRNoAddition><AdditionToEnergyFrameDueToSpecialConditions>0</AdditionToEnergyFrameDueToSpecialConditions><TotalEnergyRequirement>59.721000000000000000000000000</TotalEnergyRequirement><ContributionToEnergyRequirementHeating>0.00</ContributionToEnergyRequirementHeating></RenovationClass2><RenovationClass1><EnergyFrameInBRNoAddition>40</EnergyFrameInBRNoAddition><AdditionToEnergyFrameDueToSpecialConditions>0</AdditionToEnergyFrameDueToSpecialConditions><TotalEnergyRequirement>59.721000000000000000000000000</TotalEnergyRequirement><ContributionToEnergyRequirementHeating>0.00</ContributionToEnergyRequirementHeating></RenovationClass1><EnergyFrame2018><EnergyFrameInBRNoAddition>40</EnergyFrameInBRNoAddition><AdditionToEnergyFrameDueToSpecialConditions>0</AdditionToEnergyFrameDueToSpecialConditions><TotalEnergyRequirement>59.721000000000000000000000000</TotalEnergyRequirement><ContributionToEnergyRequirementHeating>0.00</ContributionToEnergyRequirementHeating><ContributionToEnergyRequirementElectricity>59.721000000000000000000000000</ContributionToEnergyRequirementElectricity><ContributionToEnergyRequirementExcessTemperature>0.00</ContributionToEnergyRequirementExcessTemperature></EnergyFrame2018><LowEnergyFrame><EnergyFrameInBRNoAddition>27</EnergyFrameInBRNoAddition><AdditionToEnergyFrameDueToSpecialConditions>0</AdditionToEnergyFrameDueToSpecialConditions><TotalEnergyRequirement>59.721000000000000000000000000</TotalEnergyRequirement><ContributionToEnergyRequirementHeating>0.00</ContributionToEnergyRequirementHeating><ContributionToEnergyRequirementElectricity>59.721000000000000000000000000</ContributionToEnergyRequirementElectricity><ContributionToEnergyRequirementExcessTemperature>0.00</ContributionToEnergyRequirementExcessTemperature></LowEnergyFrame></KeyFigures></CalculatedBe18Result></ResultForAllProposals></ZoneResult></ZoneResults></ResultData><PDFReportData xmlns="http://www.ens.dk/PDFReportData"><SchemaVersion>2.0.1</SchemaVersion><ReportConfiguration><ReportType>Existing</ReportType><BuildingSize>Small</BuildingSize><NewBuildApproved>NotApplicable</NewBuildApproved><Basement>NoBasement</Basement><Lighting>NoLighting</Lighting><RoofType>SlopingRoofWithUnusedArea</RoofType><DestructiveInspections>DestructiveInspectionsNotAllowed</DestructiveInspections></ReportConfiguration><Name /><StreetNameAndHouseNumber>Sønderskovvej 5</StreetNameAndHouseNumber><PostalCodeAndCity>5932 Humble</PostalCodeAndCity><CurrentEnergyLabelClassification>C</CurrentEnergyLabelClassification><AllProfitableProposalsEnergyLabelClassification>B</AllProfitableProposalsEnergyLabelClassification><AllProposalsEnergyLabelClassification>A2010</AllProposalsEnergyLabelClassification><ValidFrom>2026-04-24</ValidFrom><ValidTo>2036-04-24</ValidTo><EnergyLabelSerialIdentifier>311896657</EnergyLabelSerialIdentifier><CompanyName>Botjek A/S</CompanyName><CompanyNumber>600078</CompanyNumber><CompanyVatNumber>30711602</CompanyVatNumber><CompanyStreetNameAndHouseNumber>Botjek Center Fyn, Thriges Plads 10</CompanyStreetNameAndHouseNumber><CompanyPostalCodeAndCity>5000 Odense C</CompanyPostalCodeAndCity><CompanyWebsite>www.botjek.dk</CompanyWebsite><CompanyEmail>fyn@botjek.dk</CompanyEmail><CompanyPhoneNumber>70261199</CompanyPhoneNumber><ConsultantName>Michael Bo Bang </ConsultantName><Recommendations><ProposalGroupReference ProposalGroupID="3" /></Recommendations><BuildingReview><Text ID="0"><BIClassification>1-1-1-0</BIClassification><BuildingName>Hovedbygning</BuildingName><StatusText>Loftsrum vurderes isoleret med 200 mm mineraluld. Konstruktionstykkelse er målt ved loftlem. Konstruktionstykkelse, sammenholdt med opførelsesår, ligger til grund for skønnet af isoleringsforholdet.</StatusText><ProposalGroups><ProposalGroup ID="0"><Category>ProfitableWhenRenovating</Category><ShortText>Efterisolering af loftsrum med 150 mm isolering til 350 mm</ShortText><LongText>Efterisolering af loftsrum med 150 mm isolering. Eksisterende isolering bevares, så der efter fremtidige forhold er isoleret med 350 mm. Der etableres ny gangbro i tagrummet, eller hvis der findes en eksisterende, skal denne hæves til de nye isoleringsforhold.</LongText><CO2Saving>0.06067600</CO2Saving><MoneySaving>600</MoneySaving></ProposalGroup></ProposalGroups></Text><Text ID="1"><BIClassification>1-2-2-0</BIClassification><BuildingName>Hovedbygning</BuildingName><StatusText>Ydervægge består af 24 cm massiv teglvæg med indvendig pladebeklædning og 150 mm isolering. Konstruktions- og isoleringsforhold er baseret på ejers oplysninger.
Konstruktionstykkelse er målt ved vindue. Konstruktionstykkelse, sammenholdt med opførelsesår, ligger til grund for skønnet af isoleringsforholdet.</StatusText><ProposalGroups /></Text><Text ID="2"><BIClassification>1-3-1-0</BIClassification><BuildingName>Hovedbygning</BuildingName><StatusText>Oplukkelige vinduer med flere fag. Vinduerne er monteret med tolags termorude.</StatusText><ProposalGroups><ProposalGroup ID="1"><Category>ProfitableWhenRenovating</Category><ShortText>Udskiftning af eksisterende flerfagsvinduer</ShortText><LongText>Eksisterende flerfagsvinduer foreslås udskiftet til nye vinduer med energiruder, energiklasse A.</LongText><CO2Saving>0.12785300</CO2Saving><MoneySaving>1100</MoneySaving></ProposalGroup></ProposalGroups></Text><Text ID="3"><BIClassification>1-3-3-0</BIClassification><BuildingName>Hovedbygning</BuildingName><StatusText>Yderdør med enkeltfagsvindue, monteret med tolags termoruder.

Yderdør med enkeltfagsvindue, monteret med tolags termoruder.</StatusText><ProposalGroups><ProposalGroup ID="2"><Category>ProfitableWhenRenovating</Category><ShortText>Udskiftning af eksisterende yderdøre</ShortText><LongText>Eksisterende yderdøre foreslås udskiftet til nye døre med bedre isolering og tæthed.</LongText><CO2Saving>0.03368700</CO2Saving><MoneySaving>300</MoneySaving></ProposalGroup></ProposalGroups></Text><Text ID="4"><BIClassification>1-4-1-0</BIClassification><BuildingName>Hovedbygning</BuildingName><StatusText>Terrændæk er udført af beton med slidlagsgulv. Gulvet er isoleret med 300 mm polystyrenplader under betonen. Konstruktions- og isoleringsforhold er baseret på ejers oplysninger.
( U-værdi tillæg påført: 0.07 W/m2K)</StatusText><ProposalGroups /></Text><Text ID="5"><BIClassification>1-5-1-0</BIClassification><BuildingName>Hovedbygning</BuildingName><StatusText>Der er naturlig ventilation i hele ejendommen. Ejendommen er normal tæt, da konstruktionssamlinger og fuger ved vindues- og døråbninger, samt tætningslister i vinduer og udvendige døre fremstår i god stand.</StatusText><ProposalGroups /></Text><Text ID="6"><BIClassification>1-6-1-0</BIClassification><BuildingName>Hovedbygning</BuildingName><StatusText>Internt varmetilskud for enfamiliebyggeri.</StatusText><ProposalGroups /></Text><Text ID="7"><BIClassification>2-1-1-0</BIClassification><BuildingName>Hovedbygning</BuildingName><StatusText>Ejendommen opvarmes med varmepumpe.</StatusText><ProposalGroups /></Text><Text ID="8"><BIClassification>2-1-5-0</BIClassification><BuildingName>Hovedbygning</BuildingName><StatusText>Bygningen opvarmes med en luft/vand-varmepumpe af mærket Vølund F2025-10. Selve indedelen er placeret i teknikrum. Indregning af pumpens ydelser er udført iht. producentens anvisninger.</StatusText><ProposalGroups /></Text><Text ID="9"><BIClassification>2-1-6-0</BIClassification><BuildingName>Hovedbygning</BuildingName><StatusText>Der er ikke stillet forslag til solvarmeanlæg, da dette, med bygningens eksisterende varmeanlæg og den dertilhørende energipris, ikke vil kunne medføre et fornuftigt og rentabelt forslag.</StatusText><ProposalGroups /></Text><Text ID="10"><BIClassification>2-2-1-0</BIClassification><BuildingName>Hovedbygning</BuildingName><StatusText>Den primære opvarmning af ejendommen sker via gulvvarme i opvarmede rum. Til hvert rum er fremført gulvvarmeslanger placeret i gulv. Rør er tilsluttet fordelerrør.</StatusText><ProposalGroups /></Text><Text ID="11"><BIClassification>2-2-3-0</BIClassification><BuildingName>Hovedbygning</BuildingName><StatusText>Varmeanlægget er forsynet med en varmefordelingspumpe af fabrikat Grundfos type UPM3 15-70 130/25-70 130/25-70 180 - 52 W med en nominel effekt på 52 W. Pumpen er placeret i teknikrummet og er fra perioden 2022. </StatusText><ProposalGroups /></Text><Text ID="12"><BIClassification>3-1-1-0</BIClassification><BuildingName>Hovedbygning</BuildingName><StatusText>I beregningen er der indregnet et varmtvandsforbrug på 250 liter pr. m² opvarmet etageareal pr. år.</StatusText><ProposalGroups /></Text><Text ID="13"><BIClassification>3-1-5-0</BIClassification><BuildingName>Hovedbygning</BuildingName><StatusText>Varmt brugsvand produceres via varmtvandsbeholder der er integreret i kedel.</StatusText><ProposalGroups /></Text><Text ID="14"><BIClassification>4-1-3-0</BIClassification><BuildingName>Hovedbygning</BuildingName><StatusText>Der er ingen solceller på bygningen.</StatusText><ProposalGroups><ProposalGroup ID="3"><Category>Profitable</Category><ShortText>Montage af nye solceller</ShortText><LongText>Montering af solceller på tagflade mod syd . Det anbefales at der monteres solceller af typen Monokrystallinske silicium med et areal på ca. 20 m². Det forslåede anlæg har en effekt på 4,2 kW. For at opnå optimal virkningsgrad kan det være nødvendigt at beskære eventuelle trækroner, så der ikke opstår skyggevirkning på solcellerne. Det bør undersøges, om den eksisterende tagkonstruktion er egnet til den ekstra vægt fra solcellerne. En eventuel udgift til dette er ikke medtaget i forslagets økonomi. I det foreslåede anlæg er der ikke  taget højde for eventuelle restriktioner i forhold til Planlovsbestemmelser herunder lokalplan m.v. 
Modsat solvarme og varmepumpe, supplerer solceller strømforsyningen og ikke varmeforsyningen, hvis der ikke anvendes el til opvarmning af bygningen.</LongText><Investment>40800</Investment><CO2Saving>0.8870910000000000000000000</CO2Saving><MoneySaving>3300</MoneySaving><ImplementationReferenceText>Solcelleanlæg</ImplementationReferenceText><ImplementationReferenceLink>www.sparenergi.dk/solcelleanlaeg</ImplementationReferenceLink><RenovationTime>Fra 1 uge til 2 uger</RenovationTime></ProposalGroup></ProposalGroups></Text></BuildingReview><FuelEconomies><FuelEconomy><Title>El til opvarmning</Title><YearlyCostDkk>8900</YearlyCostDkk><YearlyCostDkkAfterProfitableProposals>7300</YearlyCostDkkAfterProfitableProposals><SavingDkkAfterProfitableProposals>1600</SavingDkkAfterProfitableProposals></FuelEconomy><FuelEconomy><Title>El til andet</Title><YearlyCostDkk>5300</YearlyCostDkk><YearlyCostDkkAfterProfitableProposals>4000</YearlyCostDkkAfterProfitableProposals><SavingDkkAfterProfitableProposals>1300</SavingDkkAfterProfitableProposals></FuelEconomy><FuelEconomy><Title>Overskud fra solceller</Title><YearlyCostDkk>0</YearlyCostDkk><YearlyCostDkkAfterProfitableProposals>-500</YearlyCostDkkAfterProfitableProposals><SavingDkkAfterProfitableProposals>500</SavingDkkAfterProfitableProposals></FuelEconomy></FuelEconomies><TotalFuelEconomy><YearlyCostDkk>14200</YearlyCostDkk><YearlyCostDkkAfterProfitableProposals>10800</YearlyCostDkkAfterProfitableProposals><SavingDkkAfterProfitableProposals>3400</SavingDkkAfterProfitableProposals></TotalFuelEconomy><TotalCo2Emissions><YearlyEmissionTon>1.70</YearlyEmissionTon><YearlyEmissionTonAfterProfitableProposals>0.82</YearlyEmissionTonAfterProfitableProposals><SavingTonAfterProfitableProposals>0.89</SavingTonAfterProfitableProposals></TotalCo2Emissions><Prices><Price><Title>Elektricitet til opvarmning</Title><FuelUnit>kWh</FuelUnit><Price>1.63</Price></Price><Price><Title>Elektricitet til andet end opvarmning</Title><FuelUnit>kWh</FuelUnit><Price>1.63</Price></Price></Prices><Buildings><Building><NameOrNumber>Hovedbygning</NameOrNumber><StreetNameAndHouseNumber>Sønderskovvej 5</StreetNameAndHouseNumber><PostalCodeAndCity>5932 Humble</PostalCodeAndCity><BBRNumber>482-5790-1</BBRNumber><BBRUsage>Fritliggende enfamilieshus (parcelhus) (120)</BBRUsage><BFENumber>3072422</BFENumber><YearOfConstruction>1850</YearOfConstruction><YearOfRenovation>1963</YearOfRenovation><PrimaryHeatSupplyType>El, Varmepumpe</PrimaryHeatSupplyType><SecondaryHeatSupplyType>Ingen</SecondaryHeatSupplyType><BBRDwellingArea>100</BBRDwellingArea><BBRCommercialArea>0</BBRCommercialArea><TotalHeatedArea>100</TotalHeatedArea><HeatedTopFloorAreaOfTotalHeatedArea>0</HeatedTopFloorAreaOfTotalHeatedArea><HeatedBasementAreaOfTotalHeatedArea>0</HeatedBasementAreaOfTotalHeatedArea><UnheatedBasementArea>0</UnheatedBasementArea><CurrentEnergyLabelClassification>C</CurrentEnergyLabelClassification><AllProfitableProposalsEnergyLabelClassification>B</AllProfitableProposalsEnergyLabelClassification><AllProposalsEnergyLabelClassification>A2010</AllProposalsEnergyLabelClassification><FuelExchanges><HeatingConsumptions><HeatingConsumption><Title>Elektricitet</Title><FuelUnit>kWh</FuelUnit><FuelMaterial>elektricitet</FuelMaterial><FuelAmount>5441.00</FuelAmount><kWhAmount>5441</kWhAmount></HeatingConsumption></HeatingConsumptions><OtherElectricalConsumptions><OtherElectricalConsumption><Title>El til bygningsdrift</Title><kWhAmount>143</kWhAmount></OtherElectricalConsumption><OtherElectricalConsumption><Title>El til forbrug</Title><kWhAmount>3066</kWhAmount></OtherElectricalConsumption></OtherElectricalConsumptions><Productions /></FuelExchanges><ReportedConsumptions /><ReportedConsumptionAdjustedToStandardYear /></Building></Buildings><AdditionalComments>Bygningsdelenes isoleringsevne er baseret på skøn ud fra registrerede isoleringstykkelser, og er heraf fastlagt ud fra tabeller i gældende håndbog for energikonsulenter, som sammen med gældende DS 418 og f.eks Rockwool Energy Design danner grundlag for beregninger af yderligere konstruktioner.

Der gøres opmærksom på, at forslag vedr. efterisolering af bygningskonstruktioner som f.eks. gulve, lofter og vægge alene er beregnet ud fra et energimæssigt hensyn. Der er i forslagene ikke taget højde for byggetekniske konsekvenser af forslagene. 

Det anbefales generelt at kontakte en rådgiver/fagmand, for at få udarbejdet en detaljeret projektbeskrivelse før isolerings- og/eller ombygningsarbejder igangsættes. I forbindelse med rapportens forslag om energiforbedring af tekniske installationer, bør man altid søge teknisk sparring med en professionel rådgiver eller leverandør. I forhold til energimærkets gyldighedsperiode, vil både prisgrundlag og produktudviklingen kunne ændre sig en del, år for år.

Ved bygningsgennemgangen forelå udfyldt ejeroplysningsskema.

Renoveringstider, som fremgår ved "Rentable forslag", er estimerede tider.

Det er vigtigt at være opmærksom på, at energimæssige forbedringer ikke kun har betydning for bygningens energiforbrug, men også for den daglige komfort, samt for en eventuel gensalgsværdi for ejendommen.  
                                                                                                                                                                                                                                                               
Svingende energipriser har ikke betydning for bygningers energimærke, men har indflydelse på energiøkonomien. 

Ved høje energipriser kan værdien af besparelsesforslag blive større, hvilket betyder, at det kan give økonomisk mening at gennemføre flere forslag inklusiv forslag der kan være rentable, hvis de udføres sammen med andre renoveringer.

Ved lave energipriser kan værdien af besparelsesforslag blive mindre og/eller umiddelbart ikke økonomisk rentable. I forbindelse hermed, er det vigtigt at være opmærksom på, at energimæssige forbedringer ikke kun har betydning for bygningens energiforbrug, men også for den daglige komfort, samt for en eventuel gensalgsværdi for ejendommen.</AdditionalComments><CommentsOnEnergyPrices>Der er i energimærket anvendt aktuelle energipriser for el.

Rapportens elpris er anvendt ud fra en gennemsnitsvurdering, da energipriserne varierer dagligt og i forhold til valg af leverandør.
 
Til beregning af rapportens forbedringsforslag er der anvendt estimerede priser, der kan variere en del fra aktuelle tilbudspriser, afhængig af både regionale forhold og valg af leverandør. 
I forbindelse med rapportens forslag om energiforbedringer, bør man altid søge  sparring med en professionel rådgiver eller leverandør. 
I forhold til energimærkets gyldighedsperiode, vil både prisgrundlag og produktudviklingen kunne ændre sig en del, år for år.</CommentsOnEnergyPrices><CommentsOnBuildingDescription>De opmålte opvarmede arealer og BBR-arealer, samt opførelsestidspunkt og evt. renoveringstidspunkt, kan ses under baggrundsinformation.

Ejendommen er kontrolopmålt af energikonsulenten ud fra stikprøver og bygningstegninger. 

De opmålte opvarmede arealer stemmer overens med BBR-meddelelsen. 

Arealerne forudsættes jf. gældende Håndbog for energikonsulenter opvarmet med samme opvarmningsform som resten af bygningen, uanset at der ingen varmekilde er, da det vurderes at eksisterende varmeanlæg er tilstrækkelig til at kunne opvarme hele boligen 

Hvis ikke andet er angivet, så er de faktuelle oplysninger i energimærket baseret på skøn ud fra hvad der visuelt kan konstateres. Oplysningerne er ikke en garanti og kan ikke betragtes som dette, men er angivet for at informere om hvad der er anvendt som grundlag for beregningen.</CommentsOnBuildingDescription></PDFReportData><EnergyLabelSoftwareSpecificData><AdditionsToEnergyFrame><ZoneAddition><ID>0</ID><AdditionToExistingNonCompliant /><AdditionToEnergyFrameBR08 /><AdditionToEnergyFrame2010 /><AdditionToEnergyFrame2015 /><AdditionToEnergyFrame2018 /><AdditionToEnergyFrame2020 /></ZoneAddition></AdditionsToEnergyFrame></EnergyLabelSoftwareSpecificData></EnergyLabel>